{
    "oci": {
        "configFile" : "~/.oci/config",
        "profile" : "API-USER",
        "compartment" : "ocid1.compartment.oc1..aaaaaaaac3cxhzoka75zaaysugzmvhm3ni3keqvikawjxvwpz26mud622owa"
    },
    "db": {
        "dsn": "innovationlab_medium",
        "username": "ONNOVATE",
        "password": "Welcome_2025",
        "walletPath": "/Users/ashish/.workshop/inno_wallet",
        "tablePrefix" : "asagarwa",
        "walletPass" : "41_innovation"
    },
    
    "agent": {
        "session": false,
        "endpoint": "ocid1.genaiagentendpoint.oc1.us-chicago-1.amaaaaaaghwivzaamiuzkcah5roqh4lyguzro7f7d25kjp36zqpjn7g5mmia",
        "no_session_endpoint": "ocid1.genaiagentendpoint.oc1.us-chicago-1.amaaaaaaghwivzaasclnx2dbalx56ot2nll7oygholltqfgszdebfszhuyqq"
    },
    "bucket": {
        "namespace": "axaemuxiyife",
        "bucketName": "InnovationLabBucket",
        "prefix": "asagarwa"
    }
    
}